trio3270/__init__.py
trio3270/_base.py
trio3270/_consts.py
trio3270/_version.py
trio3270/util.py
trio3270/_tests/__init__.py
trio3270/_tests/_samples.py
trio3270/_tests/conftest.py
trio3270/_tests/test_buffer.py
trio3270/_tests/test_checker.py
trio3270/_tests/test_example.py
trio3270/_tests/test_screen.py
trio3270/data/ws3270.exe
trio3270/screen/__init__.py
trio3270/screen/_screen.py
trio3270/screen/buffer.py
trio3270-0.2.2.dist-info/LICENSE
trio3270-0.2.2.dist-info/METADATA
trio3270-0.2.2.dist-info/WHEEL
trio3270-0.2.2.dist-info/top_level.txt
trio3270-0.2.2.dist-info/RECORD
